scrapyrunner/__init__.py
scrapyrunner/processor.py
scrapyrunner/queue.py
scrapyrunner/runner.py
scrapyrunner-0.0.10.dist-info/LICENSE
scrapyrunner-0.0.10.dist-info/METADATA
scrapyrunner-0.0.10.dist-info/WHEEL
scrapyrunner-0.0.10.dist-info/RECORD
