Metadata-Version: 2.3
Name: scrapyrunner
Version: 0.0.10
Summary: A Python library to run Scrapy spiders directly from your code.
License: MIT
Keywords: scrapy,scraping,web scraping,scrapy wrapper
Author: hupe1980
Requires-Python: >=3.10
Classifier: Framework :: Scrapy
Classifier: Intended Audience :: Developers
Classifier: License :: OSI Approved :: MIT License
Classifier: Programming Language :: Python :: 3
Classifier: Programming Language :: Python :: 3.10
Classifier: Programming Language :: Python :: 3.11
Classifier: Programming Language :: Python :: 3.12
Classifier: Programming Language :: Python :: 3.13
Requires-Dist: scrapy (>=2.12.0,<3.0.0)
Requires-Dist: twisted (>=24.11.0,<25.0.0)
Project-URL: Homepage, https://github.com/hupe1980/scrapyrunner
Project-URL: Repository, https://github.com/hupe1980/scrapyrunner
